negromate/karaoke/__init__.py
negromate/karaoke/karaoke.py
negromate/karaoke/commands/__init__.py
negromate/karaoke/commands/karaoke.py
negromate/karaoke/kv_templates/karaoke.kv
negromate/karaoke/resources/fonts/CyrBit.ttf
negromate/karaoke/resources/images/fondo_monkey_island_barco.png
negromate/karaoke/resources/images/fondo_monkey_island_pareja.png
negromate/karaoke/resources/images/logo.png
negromate.karaoke-1.2.dist-info/LICENSE.txt
negromate.karaoke-1.2.dist-info/METADATA
negromate.karaoke-1.2.dist-info/WHEEL
negromate.karaoke-1.2.dist-info/entry_points.txt
negromate.karaoke-1.2.dist-info/top_level.txt
negromate.karaoke-1.2.dist-info/RECORD
