Metadata-Version: 2.1
Name: negromate.karaoke
Version: 1.2
Summary: Player for NegroMate karaoke parties
Home-page: http://negromate.rocks
Author: Ales (Shagi) Zabala Alava
Author-email: shagi@gisa-elkartea.org
License: GPLv3
Classifier: Development Status :: 5 - Production/Stable
Classifier: Environment :: X11 Applications
Classifier: License :: OSI Approved :: GNU General Public License v3 or later (GPLv3+)
Classifier: Programming Language :: Python :: 3
Classifier: Topic :: Games/Entertainment
Classifier: Topic :: Multimedia :: Graphics :: Presentation
Requires-Python: >=3.4
License-File: LICENSE.txt
Requires-Dist: negromate.songs>=1.5
